<?xml version="1.0" encoding="ISO-8859-1" standalone="no"?>
<questions>
<!-- Question number: 1 -->
<question number="1">
<questionType typeNr="1">Text answers type</questionType>
<image>image url</image>
<question>Welk land is bekend om zijn piramides? </question>
<answers>
<answer number="1">Jordanië</answer>
<answer number="2">Egypte</answer>
<answer number="3">Israël</answer>
<answer number="4">Libië</answer>
</answers>
<correctAnswer>2</correctAnswer>
</question>
<!-- Question number: 2 -->
<question number="2">
<questionType typeNr="1">Text answers type</questionType>
<image>image url</image>
<question>Waar komen de Maya's vandaan?</question>
<answers>
<answer number="1">Zuid-Amerika</answer>
<answer number="2">Afrika</answer>
<answer number="3">Noord-Amerika</answer>
<answer number="4">Azië</answer>
</answers>
<correctAnswer>1</correctAnswer>
</question>
<!-- Question number: 3 -->
<question number="3">
<questionType typeNr="1">Text answers type</questionType>
<image>image url</image>
<question>Waar komen de Vikingen vandaan?</question>
<answers>
<answer number="1">IJsland</answer>
<answer number="2">Alaska</answer>
<answer number="3">Groenland</answer>
<answer number="4">Scandinavië</answer>
</answers>
<correctAnswer>4</correctAnswer>
</question>
<!-- Question number: 4 -->
<question number="4">
<questionType typeNr="1">Text answers type</questionType>
<image>image url</image>
<question>Waar varen de Vinkingen mee?</question>
<answers>
<answer number="1">Drakar</answer>
<answer number="2">Kano</answer>
<answer number="3">Fluisterboot</answer>
<answer number="4">Surfplank</answer>
</answers>
<correctAnswer>1</correctAnswer>
</question>
<!-- Question number: 5 -->
<question number="5">
<questionType typeNr="1">Text answers type</questionType>
<image>image url</image>
<question>Hoe heet het gevecht tussen ridders?</question>
<answers>
<answer number="1">Duel</answer>
<answer number="2">Strooispel</answer>
<answer number="3">Steekspel</answer>
<answer number="4">Ronde</answer>
</answers>
<correctAnswer>3</correctAnswer>
</question>
<!-- Question number: 6 -->
<question number="6">
<questionType typeNr="1">Text answers type</questionType>
<image>image url</image>
<question>Waar werd in de Middeleeuwen het vuilnis gelaten?</question>
<answers>
<answer number="1">Het werd verbrand</answer>
<answer number="2">De container</answer>
<answer number="3">In de zee</answer>
<answer number="4">Op straat</answer>
</answers>
<correctAnswer>4</correctAnswer>
</question>
<!-- Question number: 7 -->
<question number="7">
<questionType typeNr="1">Text answers type</questionType>
<image>image url</image>
<question>Wie was de baas van het Rijk der Nederlanden?</question>
<answers>
<answer number="1">Willem van Oranje</answer>
<answer number="2">Napoleon</answer>
<answer number="3">Mozart</answer>
<answer number="4">Bush</answer>
</answers>
<correctAnswer>1</correctAnswer>
</question>
<!-- Question number: 8 -->
<question number="8">
<questionType typeNr="1">Text answers type</questionType>
<image>image url</image>
<question>Uit welke landen bestond het Rijk der Nederlanden?</question>
<answers>
<answer number="1">Luxemburg, Nederland, Groot-Brittannië</answer>
<answer number="2">Groot-Brittannië, Nederland, Frankrijk</answer>
<answer number="3">Duitsland, Nederland, België</answer>
<answer number="4">Nederland, België, Luxemburg</answer>
</answers>
<correctAnswer>4</correctAnswer>
</question>
<!-- Question number: 9 -->
<question number="9">
<questionType typeNr="1">Text answers type</questionType>
<image>image url</image>
<question>Waar kwamen de slaven voornamelijk vandaan?</question>
<answers>
<answer number="1">Amerika</answer>
<answer number="2">Australië</answer>
<answer number="3">Afrika</answer>
<answer number="4">Europa</answer>
</answers>
<correctAnswer>3</correctAnswer>
</question>
<!-- Question number: 10 -->
<question number="10">
<questionType typeNr="2">Image answers type</questionType>
<image>image url</image>
<question>Wie was Mozart?</question>
<answers>
<answer number="1">(4 afbeeldingen)</answer>
<answer number="2">(4 afbeeldingen)</answer>
<answer number="3">(4 afbeeldingen)</answer>
<answer number="4">(4 afbeeldingen)</answer>
</answers>
<correctAnswer>4</correctAnswer>
</question>
<!-- Question number: 11 -->
<question number="11">
<questionType typeNr="1">Text answers type</questionType>
<image>image url</image>
<question>Op welk instrument speelde Mozart?</question>
<answers>
<answer number="1">Tuba</answer>
<answer number="2">Triangel</answer>
<answer number="3">Klavier</answer>
<answer number="4">Saxofoon</answer>
</answers>
<correctAnswer>3</correctAnswer>
</question>
<!-- Question number: 12 -->
<question number="12">
<questionType typeNr="1">Text answers type</questionType>
<image>image url</image>
<question>Tussen wie speelde de Amerikaanse burgeroorlog zich af?</question>
<answers>
<answer number="1">De blanken en zwarten</answer>
<answer number="2">Hawai en Alaska</answer>
<answer number="3">Het noorden en zuiden</answer>
<answer number="4">Het oosten en westen</answer>
</answers>
<correctAnswer>3</correctAnswer>
</question>
<!-- Question number: 13 -->
<question number="13">
<questionType typeNr="1">Text answers type</questionType>
<image>image url</image>
<question>Waarin wonen Indianen?</question>
<answers>
<answer number="1">Boomhut</answer>
<answer number="2">Flat</answer>
<answer number="3">Huis</answer>
<answer number="4">Tipi</answer>
</answers>
<correctAnswer>4</correctAnswer>
</question>
<!-- Question number: 14 -->
<question number="14">
<questionType typeNr="1">Text answers type</questionType>
<image>image url</image>
<question>Waar kwam de eerste man op de maan vandaan?</question>
<answers>
<answer number="1">Verenigde Staten</answer>
<answer number="2">Rusland</answer>
<answer number="3">Frankrijk</answer>
<answer number="4">India</answer>
</answers>
<correctAnswer>1</correctAnswer>
</question>
<!-- Question number: 15 -->
<question number="15">
<questionType typeNr="1">Text answers type</questionType>
<image>image url</image>
<question>Wanneer was de 2e wereldoorlog afgelopen?</question>
<answers>
<answer number="1">6 mei 2009</answer>
<answer number="2">3 mei 1915</answer>
<answer number="3">5 mei 1945</answer>
<answer number="4">6 mei 1977</answer>
</answers>
<correctAnswer>3</correctAnswer>
</question>
<!-- Question number: 16 -->
<question number="16">
<questionType typeNr="1">Text answers type</questionType>
<image>image url</image>
<question>Welke muur in Jeruzalem, zit vol met allemaal briefjes?</question>
<answers>
<answer number="1">Papierenmuur</answer>
<answer number="2">Doekmuur</answer>
<answer number="3">De Klaagmuur</answer>
<answer number="4">Berlijnse muur</answer>
</answers>
<correctAnswer>3</correctAnswer>
</question>
<!-- Question number: 17 -->
<question number="17">
<questionType typeNr="1">Text answers type</questionType>
<image>image url</image>
<question>Op welk werelddeel  lijden de meeste mensen honger?</question>
<answers>
<answer number="1">Antartica</answer>
<answer number="2">Afrika</answer>
<answer number="3">Azië</answer>
<answer number="4">Europa</answer>
</answers>
<correctAnswer>2</correctAnswer>
</question>
<!-- Question number: 18 -->
<question number="18">
<questionType typeNr="1">Text answers type</questionType>
<image>image url</image>
<question>Door wat waren oost en west Berlijn gescheiden?</question>
<answers>
<answer number="1">Rivier</answer>
<answer number="2">Muur</answer>
<answer number="3">Net</answer>
<answer number="4">Zee</answer>
</answers>
<correctAnswer>2</correctAnswer>
</question>
<!-- Question number: 19 -->
<question number="19">
<questionType typeNr="1">Text answers type</questionType>
<image>image url</image>
<question>Waar waren de Olypmische Spelen van 2008?</question>
<answers>
<answer number="1">Parijs</answer>
<answer number="2">Amsterdam</answer>
<answer number="3">China</answer>
<answer number="4">Barcelona</answer>
</answers>
<correctAnswer>3</correctAnswer>
</question>
<!-- Question number: 20 -->
<question number="20">
<questionType typeNr="1">Text answers type</questionType>
<image>image url</image>
<question>Wie is de koningin van Nederland?</question>
<answers>
<answer number="1">Maxima</answer>
<answer number="2">Magriet</answer>
<answer number="3">Alexia</answer>
<answer number="4">Beatrix</answer>
</answers>
<correctAnswer>4</correctAnswer>
</question>
<!-- Question number: 21 -->
<question number="21">
<questionType typeNr="1">Text answers type</questionType>
<image>image url</image>
<question>Wat is de langstlopende Nederlandse soap serie?</question>
<answers>
<answer number="1">Goede Tijden Slechte Tijden</answer>
<answer number="2">Hertenkamp</answer>
<answer number="3">Goudkust</answer>
<answer number="4">Onderweg naar morgen</answer>
</answers>
<correctAnswer>1</correctAnswer>
</question>
<!-- Question number: 22 -->
<question number="22">
<questionType typeNr="1">Text answers type</questionType>
<image>image url</image>
<question>Waar komt prinses Maxima vandaan?</question>
<answers>
<answer number="1">Argentinië</answer>
<answer number="2">Zuid-Afrika</answer>
<answer number="3">Rusland</answer>
<answer number="4">China</answer>
</answers>
<correctAnswer>1</correctAnswer>
</question>
<!-- Question number: 23 -->
<question number="23">
<questionType typeNr="1">Text answers type</questionType>
<image>image url</image>
<question>Uit hoeveel seizoenen bestaat een jaar?</question>
<answers>
<answer number="1">2</answer>
<answer number="2">4</answer>
<answer number="3">12</answer>
<answer number="4">6</answer>
</answers>
<correctAnswer>2</correctAnswer>
</question>
<!-- Question number: 24 -->
<question number="24">
<questionType typeNr="1">Text answers type</questionType>
<image>image url</image>
<question>Wat is de hoogste berg ter wereld?</question>
<answers>
<answer number="1">Kilimanjaro</answer>
<answer number="2">Mont Blanc</answer>
<answer number="3">Kompasberg</answer>
<answer number="4">Mount Everest</answer>
</answers>
<correctAnswer>4</correctAnswer>
</question>
<!-- Question number: 25 -->
<question number="25">
<questionType typeNr="1">Text answers type</questionType>
<image>image url</image>
<question>Wat is de meest gesproken taal ter wereld?</question>
<answers>
<answer number="1">Engels</answer>
<answer number="2">Russisch</answer>
<answer number="3">Chinees</answer>
<answer number="4">Spaans</answer>
</answers>
<correctAnswer>3</correctAnswer>
</question>
<!-- Question number: 26 -->
<question number="26">
<questionType typeNr="2">Image answers type</questionType>
<image>image url</image>
<question>Op welk plaatje zie je een geiser in IJsland?</question>
<answers>
<answer number="1">(4 afbeeldingen)</answer>
<answer number="2">(4 afbeeldingen)</answer>
<answer number="3">(4 afbeeldingen)</answer>
<answer number="4">(4 afbeeldingen)</answer>
</answers>
<correctAnswer>4</correctAnswer>
</question>
<!-- Question number: 27 -->
<question number="27">
<questionType typeNr="1">Text answers type</questionType>
<image>image url</image>
<question>Welke landen vallen onder Scandinavie?</question>
<answers>
<answer number="1">IJsland, Letland, Noorwegen</answer>
<answer number="2">Denemarken, Finland, Noorwegen en Zweden</answer>
<answer number="3">Finland, Noorwegen, Zweden</answer>
<answer number="4">Denemarken, Groenland, Noorwegen</answer>
</answers>
<correctAnswer>2</correctAnswer>
</question>
<!-- Question number: 28 -->
<question number="28">
<questionType typeNr="1">Text answers type</questionType>
<image>image url</image>
<question>Door welke tunnel wordt Frankrijk met Engeland verbonden?</question>
<answers>
<answer number="1">Coentunnel</answer>
<answer number="2">Mont Blanctunnel</answer>
<answer number="3">Gotthardtunnel</answer>
<answer number="4">Kanaaltunnel</answer>
</answers>
<correctAnswer>4</correctAnswer>
</question>
<!-- Question number: 29 -->
<question number="29">
<questionType typeNr="1">Text answers type</questionType>
<image>image url</image>
<question>Welk vervoersmiddel rijdt er door de de Kanaaltunnel?</question>
<answers>
<answer number="1">Trein</answer>
<answer number="2">Bus</answer>
<answer number="3">Tram</answer>
<answer number="4">Vrachtwagen</answer>
</answers>
<correctAnswer>1</correctAnswer>
</question>
<!-- Question number: 30 -->
<question number="30">
<questionType typeNr="1">Text answers type</questionType>
<image>image url</image>
<question>Wat eten Fransen tijdens het ontbijt?</question>
<answers>
<answer number="1">Croissant</answer>
<answer number="2">Witte bonen</answer>
<answer number="3">Pap</answer>
<answer number="4">Braadworst</answer>
</answers>
<correctAnswer>1</correctAnswer>
</question>
<!-- Question number: 31 -->
<question number="31">
<questionType typeNr="1">Text answers type</questionType>
<image>image url</image>
<question>Welk land wordt omringd door Frankrijk en grenst aan de Middelandse Zee? </question>
<answers>
<answer number="1">Spanje</answer>
<answer number="2">Portugal</answer>
<answer number="3">België</answer>
<answer number="4">Monaco</answer>
</answers>
<correctAnswer>4</correctAnswer>
</question>
<!-- Question number: 32 -->
<question number="32">
<questionType typeNr="1">Text answers type</questionType>
<image>image url</image>
<question>Uit hoeveeel provincies bestaat Nederland?</question>
<answers>
<answer number="1">8</answer>
<answer number="2">12</answer>
<answer number="3">4</answer>
<answer number="4">11</answer>
</answers>
<correctAnswer>2</correctAnswer>
</question>
<!-- Question number: 33 -->
<question number="33">
<questionType typeNr="1">Text answers type</questionType>
<image>image url</image>
<question>Welke drank wordt het meest gemaakt in Frankrijk?</question>
<answers>
<answer number="1">Port</answer>
<answer number="2">Cola</answer>
<answer number="3">Wijn</answer>
<answer number="4">Jenever</answer>
</answers>
<correctAnswer>3</correctAnswer>
</question>
<!-- Question number: 34 -->
<question number="34">
<questionType typeNr="1">Text answers type</questionType>
<image>image url</image>
<question>Wat kan je bekijken in het Louvre?</question>
<answers>
<answer number="1">Kunst</answer>
<answer number="2">Bekende mensen</answer>
<answer number="3">Boten</answer>
<answer number="4">Eten</answer>
</answers>
<correctAnswer>1</correctAnswer>
</question>
<!-- Question number: 35 -->
<question number="35">
<questionType typeNr="1">Text answers type</questionType>
<image>image url</image>
<question>In hoeveel delen was Duitsland vroeger verdeeld? </question>
<answers>
<answer number="1">1</answer>
<answer number="2">2</answer>
<answer number="3">4</answer>
<answer number="4">3</answer>
</answers>
<correctAnswer>2</correctAnswer>
</question>
<!-- Question number: 36 -->
<question number="36">
<questionType typeNr="1">Text answers type</questionType>
<image>image url</image>
<question>Welke hond komt van oorsprong uit Duitsland?</question>
<answers>
<answer number="1">Poedel</answer>
<answer number="2">Labrador</answer>
<answer number="3">Jack Russel</answer>
<answer number="4">Duitse herder</answer>
</answers>
<correctAnswer>4</correctAnswer>
</question>
<!-- Question number: 37 -->
<question number="37">
<questionType typeNr="1">Text answers type</questionType>
<image>image url</image>
<question>Welke gebergte ligt tussen Frankrijk en Spanje?</question>
<answers>
<answer number="1">Pyreneeën</answer>
<answer number="2">Rocky Mountains</answer>
<answer number="3">Alpen</answer>
<answer number="4">Himalaya</answer>
</answers>
<correctAnswer>1</correctAnswer>
</question>
<!-- Question number: 38 -->
<question number="38">
<questionType typeNr="1">Text answers type</questionType>
<image>image url</image>
<question>Welke dwergstaat ligt in Rome? </question>
<answers>
<answer number="1">Monaco</answer>
<answer number="2">Liechtenstein</answer>
<answer number="3">Andorra</answer>
<answer number="4">Vaticaanstad</answer>
</answers>
<correctAnswer>4</correctAnswer>
</question>
<!-- Question number: 39 -->
<question number="39">
<questionType typeNr="1">Text answers type</questionType>
<image>image url</image>
<question>Wie is de leider van de Rooms katholieke kerk?</question>
<answers>
<answer number="1">De Paus</answer>
<answer number="2">Priester</answer>
<answer number="3">Dominee</answer>
<answer number="4">Monnik</answer>
</answers>
<correctAnswer>1</correctAnswer>
</question>
<!-- Question number: 40 -->
<question number="40">
<questionType typeNr="1">Text answers type</questionType>
<image>image url</image>
<question>Wat is het meest gebruikt vervoer in Venetie?</question>
<answers>
<answer number="1">Tram</answer>
<answer number="2">Bus</answer>
<answer number="3">Boot</answer>
<answer number="4">Taxi</answer>
</answers>
<correctAnswer>3</correctAnswer>
</question>
<!-- Question number: 41 -->
<question number="41">
<questionType typeNr="1">Text answers type</questionType>
<image>image url</image>
<question>Welke talen worden gesproken in Zwitserland?</question>
<answers>
<answer number="1">Zwitsers, Duits</answer>
<answer number="2">Frans, Italiaans</answer>
<answer number="3">Duits, Frans, Italiaans</answer>
<answer number="4">Frans, Duits, Spaans</answer>
</answers>
<correctAnswer>3</correctAnswer>
</question>
<!-- Question number: 42 -->
<question number="42">
<questionType typeNr="1">Text answers type</questionType>
<image>image url</image>
<question>Welke criminele organisatie komt voor in Italië?</question>
<answers>
<answer number="1">Yakuza</answer>
<answer number="2">IRA</answer>
<answer number="3">Maffia</answer>
<answer number="4">Taliban</answer>
</answers>
<correctAnswer>3</correctAnswer>
</question>
<!-- Question number: 43 -->
<question number="43">
<questionType typeNr="2">Image answers type</questionType>
<image>image url</image>
<question>Hoe ziet een citer eruit?</question>
<answers>
<answer number="1">(4 afbeeldingen)</answer>
<answer number="2">(4 afbeeldingen)</answer>
<answer number="3">(4 afbeeldingen)</answer>
<answer number="4">(4 afbeeldingen)</answer>
</answers>
<correctAnswer>4</correctAnswer>
</question>
<!-- Question number: 44 -->
<question number="44">
<questionType typeNr="1">Text answers type</questionType>
<image>image url</image>
<question>Waar wonen de Roma's in?</question>
<answers>
<answer number="1">Tipi's</answer>
<answer number="2">Huizen</answer>
<answer number="3">Tenten</answer>
<answer number="4">Woonwagens</answer>
</answers>
<correctAnswer>4</correctAnswer>
</question>
<!-- Question number: 45 -->
<question number="45">
<questionType typeNr="1">Text answers type</questionType>
<image>image url</image>
<question>Welk Europees land bestaat uit de meeste eilanden?</question>
<answers>
<answer number="1">Noorwegen</answer>
<answer number="2">Griekenland</answer>
<answer number="3">Italië</answer>
<answer number="4">Spanje</answer>
</answers>
<correctAnswer>2</correctAnswer>
</question>
<!-- Question number: 46 -->
<question number="46">
<questionType typeNr="1">Text answers type</questionType>
<image>image url</image>
<question>Wat is de langste rivier ter wereld?</question>
<answers>
<answer number="1">Ob</answer>
<answer number="2">Nijl</answer>
<answer number="3">Amazone</answer>
<answer number="4">Mississippi</answer>
</answers>
<correctAnswer>2</correctAnswer>
</question>
<!-- Question number: 47 -->
<question number="47">
<questionType typeNr="2">Image answers type</questionType>
<image>image url</image>
<question>Op welke foto staat een eland?</question>
<answers>
<answer number="1">(4 afbeeldingen)</answer>
<answer number="2">(4 afbeeldingen)</answer>
<answer number="3">(4 afbeeldingen)</answer>
<answer number="4">(4 afbeeldingen)</answer>
</answers>
<correctAnswer>4</correctAnswer>
</question>
<!-- Question number: 48 -->
<question number="48">
<questionType typeNr="1">Text answers type</questionType>
<image>image url</image>
<question>In welke Canadese provincie is Frans de officieel gesproken taal?</question>
<answers>
<answer number="1">Ontario</answer>
<answer number="2">Quebec</answer>
<answer number="3">Nova Scotia</answer>
<answer number="4">Alberta</answer>
</answers>
<correctAnswer>2</correctAnswer>
</question>
<!-- Question number: 49 -->
<question number="49">
<questionType typeNr="1">Text answers type</questionType>
<image>image url</image>
<question>Welk vervoer wordt er vaak gebruikt in het poolgebied?</question>
<answers>
<answer number="1">Hondenslee</answer>
<answer number="2">Waterscooter</answer>
<answer number="3">Helikopter</answer>
<answer number="4">Fiets</answer>
</answers>
<correctAnswer>1</correctAnswer>
</question>
<!-- Question number: 50 -->
<question number="50">
<questionType typeNr="2">Image answers type</questionType>
<image>image url</image>
<question>Welk belangrijk beeld staat in New York?</question>
<answers>
<answer number="1">(4 afbeeldingen)</answer>
<answer number="2">(4 afbeeldingen)</answer>
<answer number="3">(4 afbeeldingen)</answer>
<answer number="4">(4 afbeeldingen)</answer>
</answers>
<correctAnswer>4</correctAnswer>
</question>
<!-- Question number: 51 -->
<question number="51">
<questionType typeNr="1">Text answers type</questionType>
<image>image url</image>
<question>Welke merk motoren komen uit Amerika?</question>
<answers>
<answer number="1">BMW</answer>
<answer number="2">Yamaha</answer>
<answer number="3">Honda</answer>
<answer number="4">Harley Davidson</answer>
</answers>
<correctAnswer>4</correctAnswer>
</question>
<!-- Question number: 52 -->
<question number="52">
<questionType typeNr="1">Text answers type</questionType>
<image>image url</image>
<question>Welke gebeurtenis speelde zich af op 11 september 2001?</question>
<answers>
<answer number="1">Aanslag op het World Trade Center in New York</answer>
<answer number="2">Verjaardag van Bush</answer>
<answer number="3">Start oorlog in Irak</answer>
<answer number="4">Dood Bin Laden</answer>
</answers>
<correctAnswer>1</correctAnswer>
</question>
</questions>
